<?xml version="1.0" encoding="UTF-8"?>
<export version="D">
  <design>
    <source>/home/elbosso/Desktop/gpswide/gpswide.sch</source>
    <date>Thu 02 Aug 2018 06:54:26 PM CEST</date>
    <tool>Eeschema 5.0.0-fee4fd1~66~ubuntu16.04.1</tool>
    <sheet number="1" name="/" tstamps="/">
      <title_block>
        <title/>
        <company/>
        <rev/>
        <date/>
        <source>gpswide.sch</source>
        <comment number="1" value=""/>
        <comment number="2" value=""/>
        <comment number="3" value=""/>
        <comment number="4" value=""/>
      </title_block>
    </sheet>
  </design>
  <components>
    <comp ref="U1">
      <value>NE555</value>
      <datasheet>http://www.ti.com/lit/ds/symlink/ne555.pdf</datasheet>
      <libsource lib="Timer" part="NE555" description="Precision Timers, DIP-8/SOIC-8"/>
      <sheetpath names="/" tstamps="/"/>
      <tstamp>5B63357A</tstamp>
    </comp>
  </components>
  <libparts>
    <libpart lib="Timer" part="LM555">
      <aliases>
        <alias>ICM7555</alias>
        <alias>LMC555xM</alias>
        <alias>LMC555xMM</alias>
        <alias>LMC555xN</alias>
        <alias>MC1455</alias>
        <alias>TLC555CD</alias>
        <alias>TLC555CP</alias>
        <alias>TLC555CPS</alias>
        <alias>NA555</alias>
        <alias>NE555</alias>
        <alias>SE555</alias>
        <alias>SA555</alias>
      </aliases>
      <description>Timer, DIP-8/SOIC-8/SSOP-8</description>
      <docs>http://www.ti.com/lit/ds/symlink/lm555.pdf</docs>
      <footprints>
        <fp>SOIC*3.9x4.9mm*P1.27mm*</fp>
        <fp>DIP*W7.62mm*</fp>
        <fp>TSSOP*3x3mm*P0.65mm*</fp>
      </footprints>
      <fields>
        <field name="Reference">U</field>
        <field name="Value">LM555</field>
      </fields>
      <pins>
        <pin num="1" name="GND" type="power_in"/>
        <pin num="2" name="TR" type="input"/>
        <pin num="3" name="Q" type="output"/>
        <pin num="4" name="R" type="input"/>
        <pin num="5" name="CV" type="input"/>
        <pin num="6" name="THR" type="input"/>
        <pin num="7" name="DIS" type="input"/>
        <pin num="8" name="VCC" type="power_in"/>
      </pins>
    </libpart>
  </libparts>
  <libraries>
    <library logical="Timer">
      <uri>/usr/share/kicad/library/Timer.lib</uri>
    </library>
  </libraries>
  <nets>
    <net code="1" name="+5V">
      <node ref="U1" pin="8"/>
    </net>
    <net code="2" name="GND">
      <node ref="U1" pin="1"/>
    </net>
    <net code="3" name="Net-(U1-Pad2)">
      <node ref="U1" pin="2"/>
    </net>
    <net code="4" name="Net-(U1-Pad3)">
      <node ref="U1" pin="3"/>
    </net>
    <net code="5" name="Net-(U1-Pad4)">
      <node ref="U1" pin="4"/>
    </net>
    <net code="6" name="Net-(U1-Pad5)">
      <node ref="U1" pin="5"/>
    </net>
    <net code="7" name="Net-(U1-Pad6)">
      <node ref="U1" pin="6"/>
    </net>
    <net code="8" name="Net-(U1-Pad7)">
      <node ref="U1" pin="7"/>
    </net>
  </nets>
</export>
